pytest_clld/__init__.py
pytest_clld/_app.py
pytest_clld/_selenium.py
pytest_clld/_selenium_common.py
pytest_clld/_selenium_datatable.py
pytest_clld/_selenium_map.py
pytest_clld/plugin.py
pytest_clld-1.3.0.dist-info/LICENSE
pytest_clld-1.3.0.dist-info/METADATA
pytest_clld-1.3.0.dist-info/WHEEL
pytest_clld-1.3.0.dist-info/entry_points.txt
pytest_clld-1.3.0.dist-info/top_level.txt
pytest_clld-1.3.0.dist-info/RECORD
