Metadata-Version: 2.1
Name: pytest-clld
Version: 1.3.0
Classifier: Framework :: Pytest
License-File: LICENSE
Requires-Dist: pytest>=3.9
Requires-Dist: clld
Requires-Dist: sqlalchemy>=1.0
Requires-Dist: WebTest>=1.3.1
Requires-Dist: pyramid>=1.6
Requires-Dist: html5lib
Requires-Dist: webob
Requires-Dist: selenium>=4.1
